{"metadata": {"dbt_schema_version": "https://schemas.getdbt.com/dbt/run-results/v4.json", "dbt_version": "1.5.4", "generated_at": "2023-08-06T14:54:40.120279Z", "invocation_id": "6a3a370b-f41f-4a72-91d0-27d5c0d40e7e", "env": {}}, "results": [{"status": "success", "timing": [{"name": "compile", "started_at": "2023-08-06T14:54:40.012497Z", "completed_at": "2023-08-06T14:54:40.017957Z"}, {"name": "execute", "started_at": "2023-08-06T14:54:40.018421Z", "completed_at": "2023-08-06T14:54:40.018432Z"}], "thread_id": "Thread-1 (worker)", "execution_time": 0.007019996643066406, "adapter_response": {}, "message": null, "failures": null, "unique_id": "model.northwind.stg_customers"}, {"status": "success", "timing": [{"name": "compile", "started_at": "2023-08-06T14:54:40.019915Z", "completed_at": "2023-08-06T14:54:40.021460Z"}, {"name": "execute", "started_at": "2023-08-06T14:54:40.021820Z", "completed_at": "2023-08-06T14:54:40.021825Z"}], "thread_id": "Thread-1 (worker)", "execution_time": 0.002699136734008789, "adapter_response": {}, "message": null, "failures": null, "unique_id": "model.northwind.stg_employees"}, {"status": "success", "timing": [{"name": "compile", "started_at": "2023-08-06T14:54:40.023102Z", "completed_at": "2023-08-06T14:54:40.025138Z"}, {"name": "execute", "started_at": "2023-08-06T14:54:40.025503Z", "completed_at": "2023-08-06T14:54:40.025507Z"}], "thread_id": "Thread-1 (worker)", "execution_time": 0.0032148361206054688, "adapter_response": {}, "message": null, "failures": null, "unique_id": "model.northwind.stg_order_details"}, {"status": "success", "timing": [{"name": "compile", "started_at": "2023-08-06T14:54:40.026757Z", "completed_at": "2023-08-06T14:54:40.029072Z"}, {"name": "execute", "started_at": "2023-08-06T14:54:40.029461Z", "completed_at": "2023-08-06T14:54:40.029465Z"}], "thread_id": "Thread-1 (worker)", "execution_time": 0.0034940242767333984, "adapter_response": {}, "message": null, "failures": null, "unique_id": "model.northwind.stg_orders"}, {"status": "success", "timing": [{"name": "compile", "started_at": "2023-08-06T14:54:40.030720Z", "completed_at": "2023-08-06T14:54:40.032474Z"}, {"name": "execute", "started_at": "2023-08-06T14:54:40.032865Z", "completed_at": "2023-08-06T14:54:40.032871Z"}], "thread_id": "Thread-1 (worker)", "execution_time": 0.0030007362365722656, "adapter_response": {}, "message": null, "failures": null, "unique_id": "model.northwind.stg_products"}, {"status": "success", "timing": [{"name": "compile", "started_at": "2023-08-06T14:54:40.034396Z", "completed_at": "2023-08-06T14:54:40.036255Z"}, {"name": "execute", "started_at": "2023-08-06T14:54:40.036621Z", "completed_at": "2023-08-06T14:54:40.036624Z"}], "thread_id": "Thread-1 (worker)", "execution_time": 0.0031189918518066406, "adapter_response": {}, "message": null, "failures": null, "unique_id": "model.northwind.stg_shippers"}, {"status": "success", "timing": [{"name": "compile", "started_at": "2023-08-06T14:54:40.038391Z", "completed_at": "2023-08-06T14:54:40.040733Z"}, {"name": "execute", "started_at": "2023-08-06T14:54:40.041131Z", "completed_at": "2023-08-06T14:54:40.041136Z"}], "thread_id": "Thread-1 (worker)", "execution_time": 0.00396418571472168, "adapter_response": {}, "message": null, "failures": null, "unique_id": "model.northwind.stg_suppliers"}, {"status": "success", "timing": [{"name": "compile", "started_at": "2023-08-06T14:54:40.042891Z", "completed_at": "2023-08-06T14:54:40.043833Z"}, {"name": "execute", "started_at": "2023-08-06T14:54:40.044372Z", "completed_at": "2023-08-06T14:54:40.044378Z"}], "thread_id": "Thread-1 (worker)", "execution_time": 0.002591848373413086, "adapter_response": {}, "message": null, "failures": null, "unique_id": "seed.northwind.seed_supplier_divisions"}, {"status": "success", "timing": [{"name": "compile", "started_at": "2023-08-06T14:54:40.046114Z", "completed_at": "2023-08-06T14:54:40.054892Z"}, {"name": "execute", "started_at": "2023-08-06T14:54:40.055429Z", "completed_at": "2023-08-06T14:54:40.055438Z"}], "thread_id": "Thread-1 (worker)", "execution_time": 0.01041102409362793, "adapter_response": {}, "message": null, "failures": null, "unique_id": "test.northwind.source_not_null_northwind_orders_order_id.5a7c008c6e"}, {"status": "success", "timing": [{"name": "compile", "started_at": "2023-08-06T14:54:40.057113Z", "completed_at": "2023-08-06T14:54:40.061497Z"}, {"name": "execute", "started_at": "2023-08-06T14:54:40.061947Z", "completed_at": "2023-08-06T14:54:40.061954Z"}], "thread_id": "Thread-1 (worker)", "execution_time": 0.005828857421875, "adapter_response": {}, "message": null, "failures": null, "unique_id": "test.northwind.source_unique_northwind_orders_order_id.4a8a4df128"}, {"status": "success", "timing": [{"name": "compile", "started_at": "2023-08-06T14:54:40.063445Z", "completed_at": "2023-08-06T14:54:40.065251Z"}, {"name": "execute", "started_at": "2023-08-06T14:54:40.065653Z", "completed_at": "2023-08-06T14:54:40.065658Z"}], "thread_id": "Thread-1 (worker)", "execution_time": 0.0030889511108398438, "adapter_response": {}, "message": null, "failures": null, "unique_id": "model.northwind.dim_customers"}, {"status": "success", "timing": [{"name": "compile", "started_at": "2023-08-06T14:54:40.067175Z", "completed_at": "2023-08-06T14:54:40.068850Z"}, {"name": "execute", "started_at": "2023-08-06T14:54:40.069233Z", "completed_at": "2023-08-06T14:54:40.069237Z"}], "thread_id": "Thread-1 (worker)", "execution_time": 0.0029942989349365234, "adapter_response": {}, "message": null, "failures": null, "unique_id": "model.northwind.dim_employees"}, {"status": "success", "timing": [{"name": "compile", "started_at": "2023-08-06T14:54:40.070522Z", "completed_at": "2023-08-06T14:54:40.072883Z"}, {"name": "execute", "started_at": "2023-08-06T14:54:40.073249Z", "completed_at": "2023-08-06T14:54:40.073254Z"}], "thread_id": "Thread-1 (worker)", "execution_time": 0.0035271644592285156, "adapter_response": {}, "message": null, "failures": null, "unique_id": "model.northwind.dim_products"}, {"status": "success", "timing": [{"name": "compile", "started_at": "2023-08-06T14:54:40.074645Z", "completed_at": "2023-08-06T14:54:40.076188Z"}, {"name": "execute", "started_at": "2023-08-06T14:54:40.076561Z", "completed_at": "2023-08-06T14:54:40.076564Z"}], "thread_id": "Thread-1 (worker)", "execution_time": 0.0027930736541748047, "adapter_response": {}, "message": null, "failures": null, "unique_id": "model.northwind.dim_shippers"}, {"status": "success", "timing": [{"name": "compile", "started_at": "2023-08-06T14:54:40.077790Z", "completed_at": "2023-08-06T14:54:40.079251Z"}, {"name": "execute", "started_at": "2023-08-06T14:54:40.079594Z", "completed_at": "2023-08-06T14:54:40.079597Z"}], "thread_id": "Thread-1 (worker)", "execution_time": 0.002536296844482422, "adapter_response": {}, "message": null, "failures": null, "unique_id": "model.northwind.dim_suppliers"}, {"status": "success", "timing": [{"name": "compile", "started_at": "2023-08-06T14:54:40.080831Z", "completed_at": "2023-08-06T14:54:40.083275Z"}, {"name": "execute", "started_at": "2023-08-06T14:54:40.083638Z", "completed_at": "2023-08-06T14:54:40.083641Z"}], "thread_id": "Thread-1 (worker)", "execution_time": 0.003593921661376953, "adapter_response": {}, "message": null, "failures": null, "unique_id": "test.northwind.not_null_dim_customers_customer_sk.8ae5836863"}, {"status": "success", "timing": [{"name": "compile", "started_at": "2023-08-06T14:54:40.084832Z", "completed_at": "2023-08-06T14:54:40.086838Z"}, {"name": "execute", "started_at": "2023-08-06T14:54:40.087192Z", "completed_at": "2023-08-06T14:54:40.087196Z"}], "thread_id": "Thread-1 (worker)", "execution_time": 0.0030968189239501953, "adapter_response": {}, "message": null, "failures": null, "unique_id": "test.northwind.unique_dim_customers_customer_sk.22a014df62"}, {"status": "success", "timing": [{"name": "compile", "started_at": "2023-08-06T14:54:40.088358Z", "completed_at": "2023-08-06T14:54:40.090444Z"}, {"name": "execute", "started_at": "2023-08-06T14:54:40.090799Z", "completed_at": "2023-08-06T14:54:40.090803Z"}], "thread_id": "Thread-1 (worker)", "execution_time": 0.003181934356689453, "adapter_response": {}, "message": null, "failures": null, "unique_id": "test.northwind.not_null_dim_products_product_sk.2a2df3e1b9"}, {"status": "success", "timing": [{"name": "compile", "started_at": "2023-08-06T14:54:40.091959Z", "completed_at": "2023-08-06T14:54:40.093952Z"}, {"name": "execute", "started_at": "2023-08-06T14:54:40.094288Z", "completed_at": "2023-08-06T14:54:40.094292Z"}], "thread_id": "Thread-1 (worker)", "execution_time": 0.003041982650756836, "adapter_response": {}, "message": null, "failures": null, "unique_id": "test.northwind.unique_dim_products_product_sk.8f20ac7c5b"}, {"status": "success", "timing": [{"name": "compile", "started_at": "2023-08-06T14:54:40.095415Z", "completed_at": "2023-08-06T14:54:40.097687Z"}, {"name": "execute", "started_at": "2023-08-06T14:54:40.098027Z", "completed_at": "2023-08-06T14:54:40.098030Z"}], "thread_id": "Thread-1 (worker)", "execution_time": 0.003314971923828125, "adapter_response": {}, "message": null, "failures": null, "unique_id": "model.northwind.fact_order_details"}, {"status": "success", "timing": [{"name": "compile", "started_at": "2023-08-06T14:54:40.099504Z", "completed_at": "2023-08-06T14:54:40.101591Z"}, {"name": "execute", "started_at": "2023-08-06T14:54:40.101957Z", "completed_at": "2023-08-06T14:54:40.101960Z"}], "thread_id": "Thread-1 (worker)", "execution_time": 0.003264904022216797, "adapter_response": {}, "message": null, "failures": null, "unique_id": "test.northwind.not_null_fact_order_details_order_id.8d47c14c82"}, {"status": "success", "timing": [{"name": "compile", "started_at": "2023-08-06T14:54:40.103145Z", "completed_at": "2023-08-06T14:54:40.107968Z"}, {"name": "execute", "started_at": "2023-08-06T14:54:40.108338Z", "completed_at": "2023-08-06T14:54:40.108342Z"}], "thread_id": "Thread-1 (worker)", "execution_time": 0.005943775177001953, "adapter_response": {}, "message": null, "failures": null, "unique_id": "test.northwind.relationships_fact_order_details_customer_fk__customer_sk__ref_dim_customers_.6edf3339b8"}, {"status": "success", "timing": [{"name": "compile", "started_at": "2023-08-06T14:54:40.109505Z", "completed_at": "2023-08-06T14:54:40.112117Z"}, {"name": "execute", "started_at": "2023-08-06T14:54:40.112474Z", "completed_at": "2023-08-06T14:54:40.112477Z"}], "thread_id": "Thread-1 (worker)", "execution_time": 0.0036878585815429688, "adapter_response": {}, "message": null, "failures": null, "unique_id": "test.northwind.relationships_fact_order_details_product_fk__product_sk__ref_dim_products_.3bdd1c130a"}, {"status": "success", "timing": [{"name": "compile", "started_at": "2023-08-06T14:54:40.113602Z", "completed_at": "2023-08-06T14:54:40.116221Z"}, {"name": "execute", "started_at": "2023-08-06T14:54:40.116590Z", "completed_at": "2023-08-06T14:54:40.116593Z"}], "thread_id": "Thread-1 (worker)", "execution_time": 0.0037009716033935547, "adapter_response": {}, "message": null, "failures": null, "unique_id": "test.northwind.relationships_fact_order_details_shipper_fk__shipper_sk__ref_dim_shippers_.def15aeab7"}, {"status": "success", "timing": [{"name": "compile", "started_at": "2023-08-06T14:54:40.117705Z", "completed_at": "2023-08-06T14:54:40.118931Z"}, {"name": "execute", "started_at": "2023-08-06T14:54:40.119251Z", "completed_at": "2023-08-06T14:54:40.119254Z"}], "thread_id": "Thread-1 (worker)", "execution_time": 0.002232074737548828, "adapter_response": {}, "message": null, "failures": null, "unique_id": "test.northwind.test_sum_qty"}], "elapsed_time": 0.33774900436401367, "args": {"log_format": "default", "profiles_dir": "/Users/railanderreis/projetos/projetos_python/projetos_dbt/projeto_01/northwind", "strict_mode": false, "print": true, "enable_legacy_logger": false, "log_path": "/Users/railanderreis/projetos/projetos_python/projetos_dbt/projeto_01/northwind/logs", "indirect_selection": "eager", "introspect": true, "populate_cache": true, "which": "generate", "version_check": true, "project_dir": "/Users/railanderreis/projetos/projetos_python/projetos_dbt/projeto_01/northwind", "exclude": [], "defer": false, "send_anonymous_usage_stats": true, "compile": true, "favor_state": false, "use_colors": true, "vars": {}, "partial_parse": true, "write_json": true, "log_format_file": "debug", "log_level": "info", "warn_error_options": {"include": [], "exclude": []}, "static_parser": true, "macro_debugging": false, "quiet": false, "select": [], "use_colors_file": true, "printer_width": 80, "log_level_file": "debug", "cache_selected_only": false}}